{"client":{"timestamp":1604529122728,"hash":"7229005d305b3c41d0e6","name":"client","files":[{"name":"NamedChunk","file":"NamedChunk.7229005d305b3c41d0e6.js"},{"name":"component-app-hash","file":"component-app-hash.client.js"},{"name":"components/auto-import/GithubCorner","file":"components/auto-import/GithubCorner.7229005d305b3c41d0e6.js"}]},"modern":{"timestamp":1604529127223,"hash":"a022ec47d6aee08bb2b8","name":"modern","files":[{"name":"NamedChunk","file":"NamedChunk.a022ec47d6aee08bb2b8.js"},{"name":"component-app-hash","file":"component-app-hash.modern.js"},{"name":"components/auto-import/GithubCorner","file":"components/auto-import/GithubCorner.a022ec47d6aee08bb2b8.js"}]}}